[
    	{
            "class":"Flatten",
			"parameters":{}
		},	{
            "class":"Convolution",
			"parameters":{"kernel": 3, "padding": "valid", "stride": 4, "nb_filter": 2048, "fct_activation": "tanh"}
		},	{
            "class":"Pooling",
			"parameters":{"op": "avg", "kernel": 5, "padding": "valid", "stride": 3}
		},	{
            "class":"Convolution",
			"parameters":{"kernel": 5, "padding": "same", "stride": 2, "nb_filter": 6, "fct_activation": "relu"}
		},	{
            "class":"Flatten",
			"parameters":{}
		},	{
            "class":"Flatten",
			"parameters":{}
		},	{
            "class":"Flatten",
			"parameters":{}
		},	{
            "class":"Flatten",
			"parameters":{}
		},	{
            "class":"Dense",
			"parameters":{"nb_neurones": 1, "fct_activation": "selu"}
		}
]